sphinxcontrib/cldomain/__init__.py
sphinxcontrib/cldomain/cldomain.lisp
sphinxcontrib/cldomain/cldomain.py
sphinxcontrib/cldomain/cldomain.ros
sphinxcontrib/cldomain/cli.lisp
sphinxcontrib/cldomain/custom_command.lisp
sphinxcontrib/cldomain/package.lisp
sphinxcontrib/cldomain/sphinxcontrib.cldomain.asd
sphinxcontrib/cldomain/test.lisp
sphinxcontrib/cldomain/test.ros
sphinxcontrib/cldomain/version.lisp-expr
sphinxcontrib/hyperspec/__init__.py
sphinxcontrib/hyperspec/hyperspec.py
sphinxcontrib_cldomain-0.19.1.dist-info/COPYING
sphinxcontrib_cldomain-0.19.1.dist-info/METADATA
sphinxcontrib_cldomain-0.19.1.dist-info/WHEEL
sphinxcontrib_cldomain-0.19.1.dist-info/top_level.txt
sphinxcontrib_cldomain-0.19.1.dist-info/RECORD
