Metadata-Version: 2.1
Name: sphinxcontrib-cldomain
Version: 0.19.1
Summary: Sphinx domain for Common Lisp
Author-email: Russell Sim <rsl@simopolis.xyz>
License: GPL-3.0-or-later
Project-URL: Homepage, https://sr.ht/~rsl/sphinxcontrib-cldomain/
Project-URL: Bug Reports, https://todo.sr.ht/~rsl/sphinxcontrib-cldomain
Project-URL: Source, https://git.sr.ht/~rsl/sphinxcontrib-cldomain
Classifier: Development Status :: 4 - Beta
Classifier: Environment :: Console
Classifier: Environment :: Web Environment
Classifier: Intended Audience :: Developers
Classifier: License :: OSI Approved :: GNU General Public License v3 or later (GPLv3+)
Classifier: Natural Language :: English
Classifier: Operating System :: OS Independent
Classifier: Programming Language :: Python :: 3.7
Classifier: Programming Language :: Python :: 3.8
Classifier: Programming Language :: Python :: 3.9
Classifier: Programming Language :: Python :: 3.10
Classifier: Topic :: Documentation
Classifier: Topic :: Utilities
Requires-Python: >=3.7
License-File: COPYING
Requires-Dist: pygments
Requires-Dist: sphinx >=7.3.0
Provides-Extra: dev
Requires-Dist: pytest ; extra == 'dev'
Requires-Dist: black ; extra == 'dev'
Requires-Dist: flake8 ; extra == 'dev'
Requires-Dist: build ; extra == 'dev'
